Metadata-Version: 2.1
Name: textract-cc2ba
Version: 1.6.3b1
Summary: Extract text from most documents, with little fuss.
Home-page: https://github.com/cc2-build-automation-cgcg/textract
Author: Dean Malmgren
Author-email: dean.malmgren@datascopeanalytics.com
License: MIT
Download-URL: https://github.com/cc2-build-automation-cgcg/textract/archives/master
Platform: UNKNOWN
Provides-Extra: pocketsphinx
